cocmd_cli/main.py
cocmd_cli-0.1.0.dist-info/METADATA
cocmd_cli-0.1.0.dist-info/WHEEL
cocmd_cli-0.1.0.dist-info/entry_points.txt
cocmd_cli-0.1.0.dist-info/RECORD
